thronescli.py
thronescli-3.5.0.dist-info/METADATA
thronescli-3.5.0.dist-info/WHEEL
thronescli-3.5.0.dist-info/entry_points.txt
thronescli-3.5.0.dist-info/licenses/LICENSE.txt
thronescli-3.5.0.dist-info/RECORD
