Metadata-Version: 2.4
Name: thronescli
Version: 3.5.0
Summary: A command line interface for the thronesdb.com card database.
Project-URL: Download, https://github.com/jimorie/thronescli/archive/v3.0.0.tar.gz
Project-URL: Homepage, https://github.com/jimorie/thronescli
Author-email: Petter Nyström <jimorie@gmail.com>
License-File: LICENSE.txt
Keywords: game of thrones,thrones,thronesdb.com
Requires-Python: >=3.6
Requires-Dist: click<9.0,>=8.1.6
Requires-Dist: clicksearch<1.0,>=0.5.0
Provides-Extra: dev
Requires-Dist: black; extra == 'dev'
Requires-Dist: build; extra == 'dev'
Requires-Dist: bump; extra == 'dev'
Requires-Dist: hatchling; extra == 'dev'
Requires-Dist: ruff; extra == 'dev'
Requires-Dist: twine; extra == 'dev'
